pyqtcountup/__init__.py
pyqtcountup/countup.py
pyqtcountup/utils.py
pyqtcountup-1.0.0.dist-info/LICENSE
pyqtcountup-1.0.0.dist-info/METADATA
pyqtcountup-1.0.0.dist-info/WHEEL
pyqtcountup-1.0.0.dist-info/top_level.txt
pyqtcountup-1.0.0.dist-info/RECORD
