Metadata-Version: 2.1
Name: pyqtcountup
Version: 1.0.0
Summary: A simple numerical data animation library for PyQt and PySide labels
Home-page: https://github.com/niklashenning/pyqtcountup
Author: Niklas Henning
Author-email: business@niklashenning.com
License: MIT
Keywords: python,pyqt,qt,label,animation,numerical data
Classifier: Programming Language :: Python :: 3
Classifier: Operating System :: OS Independent
Classifier: License :: OSI Approved :: MIT License
Requires-Python: >=3.7
License-File: LICENSE
Requires-Dist: QtPy >=2.4.1
